fontawesome_in_markdown/__init__.py
fontawesome_in_markdown/main.py
fontawesome_in_markdown-0.2.1.dist-info/licenses/LICENSE
fontawesome_in_markdown-0.2.1.dist-info/METADATA
fontawesome_in_markdown-0.2.1.dist-info/WHEEL
fontawesome_in_markdown-0.2.1.dist-info/top_level.txt
fontawesome_in_markdown-0.2.1.dist-info/RECORD
