Metadata-Version: 2.4
Name: fontawesome-in-markdown
Version: 0.2.1
Summary: Markdown extension to include FontAwesome icons with ease.
Home-page: http://stickgrinder.github.com/fontawesome-in-markdown
Author: StickGrinder
Author-email: StickGrinder <stickgrinder@gmail.com>
Project-URL: Homepage, https://github.com/stickgrinder/fontawesome-in-markdown
Project-URL: Issues, https://github.com/stickgrinder/fontawesome-in-markdown/issues
Classifier: Programming Language :: Python :: 3
Classifier: License :: OSI Approved :: GNU General Public License v3 (GPLv3)
Classifier: Operating System :: OS Independent
Requires-Python: >=3.6
License-File: LICENSE
Dynamic: author
Dynamic: home-page
Dynamic: license-file
Dynamic: requires-python
